bluesky_social_graph/__init__.py
bluesky_social_graph/main.py
bluesky_social_graph-0.1.0.dist-info/METADATA
bluesky_social_graph-0.1.0.dist-info/WHEEL
bluesky_social_graph-0.1.0.dist-info/entry_points.txt
bluesky_social_graph-0.1.0.dist-info/RECORD
