Metadata-Version: 2.1
Name: bluesky-social-graph
Version: 0.1.0
Summary: A tool to retrieve and analyze Bluesky follower/following relationships
License: MIT
Author: Victoriano Izquierdo
Author-email: victoriano@gmail.com
Requires-Python: >=3.7,<3.12
Classifier: License :: OSI Approved :: MIT License
Classifier: Programming Language :: Python :: 3
Classifier: Programming Language :: Python :: 3.7
Classifier: Programming Language :: Python :: 3.8
Classifier: Programming Language :: Python :: 3.9
Classifier: Programming Language :: Python :: 3.10
Classifier: Programming Language :: Python :: 3.11
Requires-Dist: atproto (>=0.0.6,<0.0.7)
Requires-Dist: python-dotenv (>=0.19.0,<0.20.0)
